{
  "info": {
    "authors": [
      {
        "links": "https://github.com/Tooltingsu",
        "name": "Tool_tingsu"
      }
    ],
    "bgi_version": "0.52.0",
    "description": "",
    "enable_monster_loot_split": false,
    "last_modified_time": 1762527836348,
    "map_match_method": "",
    "map_name": "Teyvat",
    "name": "G09-薄荷-挪德卡莱-帕哈岛-月矩力试验设计局",
    "tags": [],
    "type": "collect",
    "version": "1.0"
  },
  "positions": [
    {
      "action": "",
      "action_params": "",
      "id": 1,
      "move_mode": "walk",
      "type": "teleport",
      "x": 9426.4922,
      "y": 3051.522
    },
    {
      "action": "",
      "action_params": "",
      "id": 2,
      "move_mode": "walk",
      "type": "path",
      "x": 9440.8906,
      "y": 3040.7676
    },
    {
      "action": "",
      "action_params": "",
      "id": 3,
      "move_mode": "walk",
      "type": "path",
      "x": 9443.4902,
      "y": 3018.7017
    },
    {
      "action": "",
      "action_params": "",
      "id": 4,
      "move_mode": "walk",
      "type": "path",
      "x": 9432.9961,
      "y": 3069.3721
    },
    {
      "action": "",
      "action_params": "",
      "id": 5,
      "move_mode": "walk",
      "type": "path",
      "x": 9460.3984,
      "y": 3095.0303
    },
    {
      "action": "",
      "action_params": "",
      "id": 6,
      "move_mode": "walk",
      "type": "path",
      "x": 9486.7236,
      "y": 3112.791
    },
    {
      "action": "",
      "action_params": "",
      "id": 7,
      "move_mode": "walk",
      "type": "path",
      "x": 9422.3838,
      "y": 3100.2568
    },
    {
      "action": "",
      "action_params": "",
      "id": 8,
      "move_mode": "walk",
      "type": "path",
      "x": 9396.0498,
      "y": 3102.2043
    },
    {
      "action": "",
      "action_params": "",
      "id": 9,
      "move_mode": "walk",
      "type": "path",
      "x": 9405.041,
      "y": 3132.501
    },
    {
      "action": "",
      "action_params": "",
      "id": 10,
      "move_mode": "walk",
      "type": "path",
      "x": 9416.2578,
      "y": 3152.0283
    },
    {
      "action": "",
      "action_params": "",
      "id": 11,
      "move_mode": "walk",
      "type": "target",
      "x": 9390.6543,
      "y": 3160.1353
    },
    {
      "action": "",
      "action_params": "",
      "id": 12,
      "move_mode": "walk",
      "type": "teleport",
      "x": 10103.1982,
      "y": 3142.1597
    },
    {
      "action": "",
      "action_params": "",
      "id": 13,
      "move_mode": "walk",
      "type": "path",
      "x": 10099.1055,
      "y": 3160.4355
    },
    {
      "action": "",
      "action_params": "",
      "id": 14,
      "move_mode": "walk",
      "type": "path",
      "x": 10101.4609,
      "y": 3164.7034
    },
    {
      "action": "",
      "action_params": "",
      "id": 15,
      "move_mode": "walk",
      "type": "path",
      "x": 10134.8594,
      "y": 3181.8887
    },
    {
      "action": "",
      "action_params": "",
      "id": 16,
      "move_mode": "walk",
      "type": "path",
      "x": 10159.875,
      "y": 3177.9084
    },
    {
      "action": "",
      "action_params": "",
      "id": 17,
      "move_mode": "walk",
      "type": "target",
      "x": 10176.0732,
      "y": 3162.063
    },
    {
      "action": "",
      "action_params": "",
      "id": 18,
      "move_mode": "walk",
      "type": "teleport",
      "x": 9315.3896,
      "y": 3543.8374
    },
    {
      "action": "",
      "action_params": "",
      "id": 19,
      "move_mode": "walk",
      "type": "path",
      "x": 9300.6621,
      "y": 3507.3105
    },
    {
      "action": "",
      "action_params": "",
      "id": 20,
      "move_mode": "walk",
      "type": "path",
      "x": 9270.9707,
      "y": 3492.9678
    },
    {
      "action": "",
      "action_params": "",
      "id": 21,
      "move_mode": "walk",
      "type": "target",
      "x": 9264.2266,
      "y": 3507.1311
    },
    {
      "action": "",
      "action_params": "",
      "id": 22,
      "move_mode": "walk",
      "type": "teleport",
      "x": 9315.3896,
      "y": 3543.8384
    },
    {
      "action": "",
      "action_params": "",
      "id": 23,
      "move_mode": "walk",
      "type": "path",
      "x": 9328.1953,
      "y": 3577.9294
    },
    {
      "action": "",
      "action_params": "",
      "id": 24,
      "move_mode": "walk",
      "type": "path",
      "x": 9327.457,
      "y": 3632.2305
    },
    {
      "action": "",
      "action_params": "",
      "id": 25,
      "move_mode": "walk",
      "type": "path",
      "x": 9324.4307,
      "y": 3686.7451
    },
    {
      "action": "",
      "action_params": "",
      "id": 26,
      "move_mode": "walk",
      "type": "path",
      "x": 9284.6162,
      "y": 3724.7617
    },
    {
      "action": "",
      "action_params": "",
      "id": 27,
      "move_mode": "walk",
      "type": "path",
      "x": 9243.8799,
      "y": 3735.6223
    },
    {
      "action": "",
      "action_params": "",
      "id": 28,
      "move_mode": "walk",
      "type": "path",
      "x": 9212.0908,
      "y": 3775.6726
    },
    {
      "action": "",
      "action_params": "",
      "id": 29,
      "move_mode": "walk",
      "type": "path",
      "x": 9233.127,
      "y": 3786.7039
    },
    {
      "action": "",
      "action_params": "",
      "id": 30,
      "move_mode": "walk",
      "type": "path",
      "x": 9236.4385,
      "y": 3782.5522
    },
    {
      "action": "",
      "action_params": "",
      "id": 31,
      "move_mode": "walk",
      "type": "path",
      "x": 9254.7168,
      "y": 3789.6541
    },
    {
      "action": "",
      "action_params": "",
      "id": 32,
      "move_mode": "walk",
      "type": "path",
      "x": 9250.6406,
      "y": 3807.5115
    },
    {
      "action": "",
      "action_params": "",
      "id": 33,
      "move_mode": "walk",
      "type": "path",
      "x": 9227.0107,
      "y": 3824.2891
    },
    {
      "action": "combat_script",
      "action_params": "wait(0.3),keypress(T),wait(30)",
      "id": 34,
      "move_mode": "walk",
      "type": "path",
      "x": 9227.2139,
      "y": 3830.7825
    },
    {
      "action": "",
      "action_params": "",
      "id": 35,
      "move_mode": "walk",
      "type": "path",
      "x": 9509.0049,
      "y": 3920.073
    },
    {
      "action": "",
      "action_params": "",
      "id": 36,
      "move_mode": "walk",
      "type": "path",
      "x": 9486.8799,
      "y": 3930.375
    },
    {
      "action": "",
      "action_params": "",
      "id": 37,
      "move_mode": "walk",
      "type": "path",
      "x": 9538.4678,
      "y": 3918.7195
    },
    {
      "action": "",
      "action_params": "",
      "id": 38,
      "move_mode": "walk",
      "type": "path",
      "x": 9568.4844,
      "y": 3912.4097
    },
    {
      "action": "",
      "action_params": "",
      "id": 39,
      "move_mode": "walk",
      "type": "path",
      "x": 9591.9668,
      "y": 3940.0137
    },
    {
      "action": "",
      "action_params": "",
      "id": 40,
      "move_mode": "walk",
      "type": "path",
      "x": 9636.7598,
      "y": 3966.9661
    },
    {
      "action": "",
      "action_params": "",
      "id": 41,
      "move_mode": "walk",
      "type": "path",
      "x": 9659.4736,
      "y": 3987.4041
    }
  ]
}