{
  "info": {
    "name": "沙脂蛹-6折胫谷",
    "type": "collect",
    "author": "无狐",
    "version": "1.0",
    "description": "",
    "bgiVersion": "0.35.1"
  },
  "positions": [
    {
      "id": 1,
      "x": 5690.23583984375,
      "y": -706.8984375,
      "type": "teleport",
      "move_mode": "walk",
      "action": "",
      "action_params": ""
    },
    {
      "id": 2,
      "x": 5665.58935546875,
      "y": -728.56640625,
      "type": "path",
      "move_mode": "walk",
      "action": "",
      "action_params": ""
    },
    {
      "id": 3,
      "x": 5664.3623046875,
      "y": -729.5703125,
      "type": "path",
      "move_mode": "climb",
      "action": "",
      "action_params": ""
    },
    {
      "id": 4,
      "x": 5634.55224609375,
      "y": -755.203125,
      "type": "path",
      "move_mode": "walk",
      "action": "",
      "action_params": ""
    },
    {
      "id": 5,
      "x": 5597.1162109375,
      "y": -734.31005859375,
      "type": "path",
      "move_mode": "walk",
      "action": "",
      "action_params": ""
    },
    {
      "id": 6,
      "x": 5590.38232421875,
      "y": -722.3349609375,
      "type": "path",
      "move_mode": "walk",
      "action": "",
      "action_params": ""
    },
    {
      "id": 7,
      "x": 5597.87255859375,
      "y": -692.47802734375,
      "type": "path",
      "move_mode": "walk",
      "action": "",
      "action_params": ""
    },
    {
      "id": 8,
      "x": 5598.03125,
      "y": -700.54736328125,
      "type": "path",
      "move_mode": "walk",
      "action": "",
      "action_params": ""
    },
    {
      "id": 9,
      "x": 5605.59423828125,
      "y": -699.90087890625,
      "type": "path",
      "move_mode": "walk",
      "action": "",
      "action_params": ""
    }
  ]
}