{
  "info": {
    "name": "36-茉洁草-枫丹-欧庇克莱歌剧院-15个",
    "type": "collect",
    "version": "1.0",
    "description": "",
    "bgi_version": "0.42.0",
    "authors": [
      {
        "name": "不瘦五十斤不改名",
        "links": "https://github.com/PanZic"
      }
    ]
  },
  "positions": [
    {
      "id": 1,
      "action": "",
      "move_mode": "walk",
      "type": "teleport",
      "x": 3595.75,
      "y": 3254.4
    },
    {
      "id": 2,
      "x": 3610.62,
      "y": 3225.67,
      "type": "path",
      "move_mode": "walk",
      "action": ""
    },
    {
      "id": 3,
      "x": 3640.21,
      "y": 3259.76,
      "type": "path",
      "move_mode": "walk",
      "action": ""
    },
    {
      "id": 4,
      "x": 3621.63,
      "y": 3264.58,
      "type": "path",
      "move_mode": "walk",
      "action": ""
    },
    {
      "id": 5,
      "x": 3626.84,
      "y": 3278.08,
      "type": "path",
      "move_mode": "walk",
      "action": ""
    },
    {
      "id": 6,
      "x": 3606.7,
      "y": 3279.4,
      "type": "path",
      "move_mode": "walk",
      "action": ""
    },
    {
      "id": 7,
      "x": 3590.94,
      "y": 3307.72,
      "type": "path",
      "move_mode": "walk",
      "action": ""
    },
    {
      "id": 8,
      "x": 3574.58,
      "y": 3314.85,
      "type": "path",
      "move_mode": "walk",
      "action": ""
    },
    {
      "id": 9,
      "x": 3569.86,
      "y": 3338.77,
      "type": "path",
      "move_mode": "walk",
      "action": ""
    },
    {
      "id": 10,
      "x": 3646.61,
      "y": 3355.42,
      "type": "path",
      "move_mode": "walk",
      "action": ""
    },
    {
      "id": 11,
      "x": 3654.35,
      "y": 3318.96,
      "type": "path",
      "move_mode": "walk",
      "action": ""
    },
    {
      "id": 12,
      "x": 3638.69,
      "y": 3295.22,
      "type": "path",
      "move_mode": "walk",
      "action": ""
    },
    {
      "id": 13,
      "x": 3682.09,
      "y": 3292.66,
      "type": "path",
      "move_mode": "walk",
      "action": ""
    },
    {
      "id": 14,
      "x": 3717.63,
      "y": 3296.21,
      "type": "path",
      "move_mode": "walk",
      "action": ""
    },
    {
      "id": 15,
      "x": 3710.2,
      "y": 3311.76,
      "type": "path",
      "move_mode": "walk",
      "action": ""
    },
    {
      "id": 16,
      "x": 3721.47,
      "y": 3330.38,
      "type": "path",
      "move_mode": "walk",
      "action": ""
    }
  ]
}