{
  "info": {
    "name": "薄荷B60-沉玉谷-赤望台2",
    "type": "collect",
    "author": "Tool_tingsu",
    "version": "1.0",
    "description": "",
    "bgi_version": "0.42.3"
  },
  "positions": [
    {
      "id": 1,
      "x": 2628.111328125,
      "y": 1528.5341796875,
      "type": "teleport",
      "move_mode": "walk",
      "action": "",
      "action_params": ""
    },
    {
      "id": 2,
      "x": 2619.3994140625,
      "y": 1533.56103515625,
      "type": "path",
      "move_mode": "walk",
      "action": "",
      "action_params": ""
    },
    {
      "id": 3,
      "x": 2590.5888671875,
      "y": 1535.27587890625,
      "type": "path",
      "move_mode": "fly",
      "action": "stop_flying",
      "action_params": ""
    },
    {
      "id": 4,
      "x": 2585.609375,
      "y": 1517.6962890625,
      "type": "path",
      "move_mode": "walk",
      "action": "",
      "action_params": ""
    },
    {
      "id": 5,
      "x": 2579.0478515625,
      "y": 1501.3046875,
      "type": "path",
      "move_mode": "walk",
      "action": "",
      "action_params": ""
    },
    {
      "id": 6,
      "x": 2584.6064453125,
      "y": 1487.609375,
      "type": "path",
      "move_mode": "walk",
      "action": "",
      "action_params": ""
    },
    {
      "id": 7,
      "x": 2576.6005859375,
      "y": 1456.14697265625,
      "type": "path",
      "move_mode": "walk",
      "action": "",
      "action_params": ""
    },
    {
      "id": 8,
      "x": 2535.130859375,
      "y": 1430.6064453125,
      "type": "path",
      "move_mode": "walk",
      "action": "",
      "action_params": ""
    },
    {
      "id": 9,
      "x": 2529.4521484375,
      "y": 1413.61962890625,
      "type": "path",
      "move_mode": "walk",
      "action": "",
      "action_params": ""
    },
    {
      "id": 10,
      "x": 2542.9619140625,
      "y": 1390.51318359375,
      "type": "path",
      "move_mode": "walk",
      "action": "",
      "action_params": ""
    },
    {
      "id": 11,
      "x": 2544.19140625,
      "y": 1372.63525390625,
      "type": "path",
      "move_mode": "walk",
      "action": "",
      "action_params": ""
    },
    {
      "id": 12,
      "x": 2550.80078125,
      "y": 1357.28076171875,
      "type": "path",
      "move_mode": "walk",
      "action": "",
      "action_params": ""
    },
    {
      "id": 13,
      "x": 2556.505859375,
      "y": 1341.62646484375,
      "type": "path",
      "move_mode": "walk",
      "action": "",
      "action_params": ""
    },
    {
      "id": 14,
      "x": 2575.9892578125,
      "y": 1326.93212890625,
      "type": "path",
      "move_mode": "walk",
      "action": "",
      "action_params": ""
    },
    {
      "id": 15,
      "x": 2587.1416015625,
      "y": 1307.17626953125,
      "type": "path",
      "move_mode": "walk",
      "action": "",
      "action_params": ""
    },
    {
      "id": 16,
      "x": 2614.4482421875,
      "y": 1296.89794921875,
      "type": "path",
      "move_mode": "walk",
      "action": "",
      "action_params": ""
    },
    {
      "id": 17,
      "x": 2619.708984375,
      "y": 1288.86865234375,
      "type": "path",
      "move_mode": "walk",
      "action": "",
      "action_params": ""
    },
    {
      "id": 18,
      "x": 2652.2392578125,
      "y": 1276.6337890625,
      "type": "path",
      "move_mode": "walk",
      "action": "",
      "action_params": ""
    },
    {
      "id": 19,
      "x": 2680.0830078125,
      "y": 1268.44580078125,
      "type": "path",
      "move_mode": "walk",
      "action": "",
      "action_params": ""
    },
    {
      "id": 20,
      "x": 2709.50390625,
      "y": 1250.5126953125,
      "type": "path",
      "move_mode": "walk",
      "action": "",
      "action_params": ""
    },
    {
      "id": 21,
      "x": 2726.25,
      "y": 1227.62646484375,
      "type": "path",
      "move_mode": "walk",
      "action": "",
      "action_params": ""
    },
    {
      "id": 22,
      "x": 2737.5732421875,
      "y": 1217.947265625,
      "type": "path",
      "move_mode": "walk",
      "action": "",
      "action_params": ""
    },
    {
      "id": 23,
      "x": 2743.5244140625,
      "y": 1210.5859375,
      "type": "path",
      "move_mode": "walk",
      "action": "",
      "action_params": ""
    },
    {
      "id": 24,
      "x": 2730.1572265625,
      "y": 1225.32080078125,
      "type": "path",
      "move_mode": "walk",
      "action": "",
      "action_params": ""
    },
    {
      "id": 25,
      "x": 2722.484375,
      "y": 1235.8681640625,
      "type": "path",
      "move_mode": "walk",
      "action": "",
      "action_params": ""
    },
    {
      "id": 26,
      "x": 2706.5654296875,
      "y": 1252.71875,
      "type": "path",
      "move_mode": "walk",
      "action": "",
      "action_params": ""
    },
    {
      "id": 27,
      "x": 2684.806640625,
      "y": 1272.998046875,
      "type": "path",
      "move_mode": "walk",
      "action": "",
      "action_params": ""
    },
    {
      "id": 28,
      "x": 2701.4775390625,
      "y": 1297.4482421875,
      "type": "path",
      "move_mode": "walk",
      "action": "",
      "action_params": ""
    },
    {
      "id": 29,
      "x": 2726.1123046875,
      "y": 1315.16845703125,
      "type": "path",
      "move_mode": "walk",
      "action": "",
      "action_params": ""
    },
    {
      "id": 30,
      "x": 2734.943359375,
      "y": 1309.41015625,
      "type": "path",
      "move_mode": "walk",
      "action": "",
      "action_params": ""
    },
    {
      "id": 31,
      "x": 2744.546875,
      "y": 1306.51025390625,
      "type": "path",
      "move_mode": "fly",
      "action": "",
      "action_params": ""
    },
    {
      "id": 32,
      "x": 2753.3193359375,
      "y": 1312.140625,
      "type": "path",
      "move_mode": "fly",
      "action": "stop_flying",
      "action_params": ""
    },
    {
      "id": 33,
      "x": 2761.740234375,
      "y": 1315.66064453125,
      "type": "path",
      "move_mode": "walk",
      "action": "",
      "action_params": ""
    },
    {
      "id": 34,
      "x": 2796.775390625,
      "y": 1327.76806640625,
      "type": "path",
      "move_mode": "fly",
      "action": "stop_flying",
      "action_params": ""
    },
    {
      "id": 35,
      "x": 2809.857421875,
      "y": 1322.61572265625,
      "type": "path",
      "move_mode": "walk",
      "action": "",
      "action_params": ""
    },
    {
      "id": 36,
      "x": 2830.9794921875,
      "y": 1313.44580078125,
      "type": "path",
      "move_mode": "walk",
      "action": "",
      "action_params": ""
    },
    {
      "id": 37,
      "x": 2856.009765625,
      "y": 1303.30126953125,
      "type": "path",
      "move_mode": "walk",
      "action": "",
      "action_params": ""
    },
    {
      "id": 38,
      "x": 2856.228515625,
      "y": 1335.9892578125,
      "type": "path",
      "move_mode": "walk",
      "action": "",
      "action_params": ""
    },
    {
      "id": 39,
      "x": 2835.7578125,
      "y": 1337.529296875,
      "type": "path",
      "move_mode": "walk",
      "action": "",
      "action_params": ""
    },
    {
      "id": 40,
      "x": 2870.69140625,
      "y": 1324.7392578125,
      "type": "path",
      "move_mode": "walk",
      "action": "",
      "action_params": ""
    },
    {
      "id": 41,
      "x": 2926.626953125,
      "y": 1334.42431640625,
      "type": "path",
      "move_mode": "walk",
      "action": "",
      "action_params": ""
    },
    {
      "id": 42,
      "x": 2979.6337890625,
      "y": 1317.638671875,
      "type": "path",
      "move_mode": "walk",
      "action": "",
      "action_params": ""
    },
    {
      "id": 43,
      "x": 2993.4140625,
      "y": 1333.328125,
      "type": "path",
      "move_mode": "walk",
      "action": "",
      "action_params": ""
    }
  ]
}