{
  "info": {
    "name": "狗粮-枫丹-伊黎耶林区-欧庇克莱歌剧院东南-2个-f",
    "type": "collect",
    "author": "Yang-z",
    "version": "1.0",
    "bgiVersion": "0.42.0"
  },
  "positions": [
    {
      "x": 3595.62,
      "y": 3254.41,
      "type": "teleport",
      "move_mode": "walk"
    },
    {
      "x": 3611.26,
      "y": 3270.22,
      "type": "path",
      "move_mode": "run"
    },
    {
      "x": 3615.74,
      "y": 3276.54,
      "type": "target",
      "move_mode": "walk",
      "action": "",
      "#": 1
    },
    {
      "x": 3611.2,
      "y": 3278.96,
      "type": "path",
      "move_mode": "walk"
    },
    {
      "x": 3594.38,
      "y": 3287.0,
      "type": "path",
      "move_mode": "run"
    },
    {
      "x": 3585.17,
      "y": 3289.4,
      "type": "target",
      "move_mode": "walk",
      "action": "",
      "#": 2
    },
    {
      "x": 3583.75,
      "y": 3290.64,
      "type": "path",
      "move_mode": "walk"
    }
  ]
}