{
  "info": {
    "name": "01-纳塔-隆崛坡-3只",
    "type": "collect",
    "version": "1.0",
    "description": "",
    "map_name": "Teyvat",
    "bgi_version": "0.45.0",
    "tags": [],
    "last_modified_time": 1753517424067,
    "authors": [
      {
        "name": "芝士贝果",
        "links": "https://github.com/cheese-bagel"
      }
    ]
  },
  "positions": [
    {
      "id": 1,
      "x": 7857.5088,
      "y": -1751.2764,
      "action": "",
      "move_mode": "walk",
      "action_params": "",
      "type": "teleport"
    },
    {
      "id": 2,
      "x": 7878.4907,
      "y": -1743.5669,
      "action": "stop_flying",
      "move_mode": "fly",
      "action_params": "",
      "type": "path"
    },
    {
      "id": 3,
      "x": 7976.5811,
      "y": -1733.4644,
      "action": "",
      "move_mode": "dash",
      "action_params": "",
      "type": "path"
    },
    {
      "id": 4,
      "x": 7988.4111,
      "y": -1737.6934,
      "action": "stop_flying",
      "move_mode": "fly",
      "action_params": "2500",
      "type": "path"
    },
    {
      "id": 5,
      "x": 7998.3745,
      "y": -1727.7495,
      "type": "path",
      "move_mode": "walk",
      "action": "",
      "action_params": ""
    },
    {
      "id": 6,
      "x": 8009.9111,
      "y": -1717.4131,
      "type": "path",
      "move_mode": "walk",
      "action": "",
      "action_params": ""
    },
    {
      "id": 7,
      "x": 8003.6279,
      "y": -1724.249,
      "type": "path",
      "move_mode": "walk",
      "action": "",
      "action_params": ""
    },
    {
      "id": 8,
      "x": 8014.6274,
      "y": -1718.3843,
      "type": "path",
      "move_mode": "walk",
      "action": "",
      "action_params": ""
    },
    {
      "id": 9,
      "x": 8020.5547,
      "y": -1710.2993,
      "type": "path",
      "move_mode": "walk",
      "action": "",
      "action_params": ""
    },
    {
      "id": 10,
      "x": 8023.0044,
      "y": -1716.2236,
      "type": "path",
      "move_mode": "walk",
      "action": "",
      "action_params": ""
    },
    {
      "id": 11,
      "x": 8030.9038,
      "y": -1730.6426,
      "type": "path",
      "move_mode": "walk",
      "action": "",
      "action_params": ""
    },
    {
      "id": 12,
      "x": 8037.1958,
      "y": -1726.5459,
      "type": "path",
      "move_mode": "walk",
      "action": "",
      "action_params": ""
    },
    {
      "id": 13,
      "x": 8029.7607,
      "y": -1729.1602,
      "type": "path",
      "move_mode": "walk",
      "action": "",
      "action_params": ""
    },
    {
      "id": 14,
      "x": 8037.6211,
      "y": -1728.4624,
      "type": "path",
      "move_mode": "walk",
      "action": "",
      "action_params": ""
    },
    {
      "id": 15,
      "x": 8038.6914,
      "y": -1722.6538,
      "type": "path",
      "move_mode": "walk",
      "action": "",
      "action_params": ""
    },
    {
      "id": 16,
      "x": 8042.6685,
      "y": -1723.7461,
      "type": "path",
      "move_mode": "walk",
      "action": "",
      "action_params": ""
    },
    {
      "id": 17,
      "x": 8042.3599,
      "y": -1716.1421,
      "type": "path",
      "move_mode": "walk",
      "action": "",
      "action_params": ""
    },
    {
      "id": 18,
      "x": 8047.7573,
      "y": -1717.4453,
      "type": "path",
      "move_mode": "walk",
      "action": "",
      "action_params": ""
    }
  ]
}