{
  "info": {
    "name": "薄荷B53-沉玉谷-赤璋城垣2",
    "type": "collect",
    "author": "Tool_tingsu",
    "version": "1.0",
    "description": "",
    "bgiVersion": "0.42.3"
  },
  "positions": [
    {
      "id": 1,
      "x": 2323.8623046875,
      "y": 1605.01416015625,
      "type": "teleport",
      "move_mode": "walk",
      "action": "",
      "action_params": "",
      "locked": false
    },
    {
      "id": 2,
      "x": 2274.3974609375,
      "y": 1602.42626953125,
      "type": "path",
      "move_mode": "walk",
      "action": "",
      "action_params": ""
    },
    {
      "id": 3,
      "x": 2244.703125,
      "y": 1590.73291015625,
      "type": "path",
      "move_mode": "walk",
      "action": "",
      "action_params": ""
    },
    {
      "id": 4,
      "x": 2235.3095703125,
      "y": 1589.7900390625,
      "type": "path",
      "move_mode": "walk",
      "action": "",
      "action_params": ""
    },
    {
      "id": 5,
      "x": 2226.7333984375,
      "y": 1589.48486328125,
      "type": "path",
      "move_mode": "walk",
      "action": "",
      "action_params": ""
    },
    {
      "id": 6,
      "x": 2220.2822265625,
      "y": 1587.00244140625,
      "type": "path",
      "move_mode": "walk",
      "action": "",
      "action_params": ""
    },
    {
      "id": 7,
      "x": 2222.9326171875,
      "y": 1560.80859375,
      "type": "path",
      "move_mode": "walk",
      "action": "",
      "action_params": ""
    },
    {
      "id": 8,
      "x": 2214.8740234375,
      "y": 1541.89013671875,
      "type": "target",
      "move_mode": "walk",
      "action": "",
      "action_params": ""
    },
    {
      "id": 9,
      "x": 2323.8623046875,
      "y": 1605.01416015625,
      "type": "teleport",
      "move_mode": "walk",
      "action": "",
      "action_params": ""
    },
    {
      "id": 10,
      "x": 2331.935546875,
      "y": 1599.181640625,
      "type": "path",
      "move_mode": "walk",
      "action": "",
      "action_params": ""
    },
    {
      "id": 11,
      "x": 2358.724609375,
      "y": 1563.43896484375,
      "type": "path",
      "move_mode": "fly",
      "action": "",
      "action_params": ""
    },
    {
      "id": 12,
      "x": 2344.1337890625,
      "y": 1541.0244140625,
      "type": "path",
      "move_mode": "walk",
      "action": "",
      "action_params": ""
    },
    {
      "id": 13,
      "x": 2355.123046875,
      "y": 1527.947265625,
      "type": "path",
      "move_mode": "walk",
      "action": "",
      "action_params": ""
    },
    {
      "id": 14,
      "x": 2375.740234375,
      "y": 1520.373046875,
      "type": "path",
      "move_mode": "walk",
      "action": "",
      "action_params": ""
    },
    {
      "id": 15,
      "x": 2364.673828125,
      "y": 1492.99169921875,
      "type": "path",
      "move_mode": "fly",
      "action": "",
      "action_params": ""
    },
    {
      "id": 16,
      "x": 2363.791015625,
      "y": 1476.3876953125,
      "type": "path",
      "move_mode": "walk",
      "action": "",
      "action_params": ""
    },
    {
      "id": 17,
      "x": 2410.828125,
      "y": 1441.30810546875,
      "type": "path",
      "move_mode": "fly",
      "action": "stop_flying",
      "action_params": "1800"
    },
    {
      "id": 18,
      "x": 2401.3681640625,
      "y": 1414.748046875,
      "type": "path",
      "move_mode": "walk",
      "action": "",
      "action_params": ""
    },
    {
      "id": 19,
      "x": 2384.55078125,
      "y": 1400.10498046875,
      "type": "path",
      "move_mode": "walk",
      "action": "",
      "action_params": ""
    },
    {
      "id": 20,
      "x": 2350.0576171875,
      "y": 1381.81787109375,
      "type": "path",
      "move_mode": "fly",
      "action": "",
      "action_params": ""
    },
    {
      "id": 21,
      "x": 2336.919921875,
      "y": 1387.990234375,
      "type": "path",
      "move_mode": "walk",
      "action": "",
      "action_params": ""
    },
    {
      "id": 22,
      "x": 2318.31640625,
      "y": 1410.25634765625,
      "type": "path",
      "move_mode": "walk",
      "action": "",
      "action_params": ""
    },
    {
      "id": 23,
      "x": 2316.3896484375,
      "y": 1419.04052734375,
      "type": "path",
      "move_mode": "walk",
      "action": "",
      "action_params": ""
    }
  ]
}