{
  "info": {
    "name": "232璃月沉玉谷灵濛山南（600_1，200_4）",
    "type": "collect",
    "author": "汐",
    "version": "1.0",
    "description": "",
    "bgiVersion": "0.42.3"
  },
  "positions": [
    {
      "id": 1,
      "x": 2002.365234375,
      "y": 2081.0283203125,
      "action": "",
      "move_mode": "walk",
      "action_params": "",
      "type": "teleport"
    },
    {
      "id": 2,
      "x": 1979.2919921875,
      "y": 2074.010986328125,
      "action": "",
      "move_mode": "dash",
      "action_params": "",
      "type": "path"
    },
    {
      "id": 3,
      "x": 1969.369140625,
      "y": 2066.48828125,
      "action": "fight",
      "move_mode": "run",
      "action_params": "",
      "type": "path"
    },
    {
      "id": 4,
      "x": 1938.4599609375,
      "y": 2042.775390625,
      "action": "",
      "move_mode": "run",
      "action_params": "",
      "type": "path"
    },
    {
      "id": 5,
      "x": 1913.87890625,
      "y": 2034.25830078125,
      "action": "",
      "move_mode": "dash",
      "action_params": "",
      "type": "path"
    },
    {
      "id": 6,
      "x": 1877.3193359375,
      "y": 2031.255859375,
      "action": "",
      "move_mode": "dash",
      "action_params": "",
      "type": "path"
    },
    {
      "id": 7,
      "x": 1868.6875,
      "y": 2059.628851155805,
      "action": "fight",
      "move_mode": "dash",
      "action_params": "",
      "type": "path"
    },
    {
      "id": 8,
      "x": 2002.392578125,
      "y": 2081.04443359375,
      "action": "",
      "move_mode": "walk",
      "action_params": "",
      "type": "teleport"
    },
    {
      "id": 9,
      "x": 1973.8642578125,
      "y": 2117.48779296875,
      "action": "",
      "move_mode": "dash",
      "action_params": "",
      "type": "path"
    },
    {
      "id": 10,
      "x": 1967.841796875,
      "y": 2151.3876953125,
      "action": "fight",
      "move_mode": "dash",
      "action_params": "",
      "type": "path"
    }
  ]
}