{
  "info": {
    "name": "A09-萃凝晶-枫丹-新枫丹科学院-9（火神赶路-3个)",
    "type": "collect",
    "authors": [
      {
        "name": "无限不循环",
        "links": "https://github.com/non-repeating001"
      }
    ],
    "version": "1.0",
    "description": "",
    "map_name": "Teyvat",
    "bgi_version": "0.45.0",
    "tags": [
      "双手剑",
      "火神赶路"
    ],
    "last_modified_time": 1755291717319,
    "enable_monster_loot_split": false,
    "map_match_method": ""
  },
  "positions": [
    {
      "id": 1,
      "x": 3811.57,
      "y": 4952.62,
      "action": "",
      "move_mode": "walk",
      "type": "teleport"
    },
    {
      "id": 2,
      "x": 3674.0488,
      "y": 4967.6689,
      "action": "combat_script",
      "move_mode": "walk",
      "action_params": "玛薇卡 w(0.15),e(hold),wait(0.05),keydown(w),wait(0.01),j,wait(0.15),j,wait(0.1),j,wait(0.01),j, wait(1.5),j,wait(0.15),j,wait(0.1),j,wait(0.01),j, wait(1.5),j,wait(0.15),j,wait(0.1),j,wait(0.01),j, wait(1.5),j,wait(0.15),j,wait(0.1),j,wait(0.01),j,wait(1.2),e;",
      "type": "orientation"
    },
    {
      "id": 3,
      "x": 3674.0498,
      "y": 4967.6694,
      "action": "",
      "move_mode": "dash",
      "action_params": "",
      "type": "path"
    },
    {
      "id": 4,
      "x": 3674.1768,
      "y": 4972.2441,
      "action": "mining",
      "move_mode": "walk",
      "action_params": "",
      "type": "target"
    },
    {
      "id": 5,
      "x": 3674.1787,
      "y": 4972.2417,
      "action": "combat_script",
      "move_mode": "walk",
      "action_params": "wait(0.5)",
      "type": "path"
    },
    {
      "id": 6,
      "x": 3674.1787,
      "y": 4972.2417,
      "action": "pick_around",
      "move_mode": "walk",
      "action_params": "",
      "type": "path"
    },
    {
      "id": 7,
      "x": 3663.6055,
      "y": 4965.6172,
      "action": "",
      "move_mode": "run",
      "action_params": "",
      "type": "path"
    },
    {
      "id": 8,
      "x": 3662.5439,
      "y": 4969.3701,
      "action": "mining",
      "move_mode": "walk",
      "action_params": "",
      "type": "target"
    },
    {
      "id": 9,
      "x": 3662.5439,
      "y": 4969.3701,
      "action": "combat_script",
      "move_mode": "walk",
      "action_params": "wait(0.5)",
      "type": "path"
    }
  ]
}