{
  "info": {
    "authors": [
      {
        "links": "",
        "name": "½"
      }
    ],
    "name": "冒险家协会_蒙德",
    "type": "collect",
    "version": "1.0",
    "bgi_version": "0.45.0",
    "map_name": "Teyvat"
  },
  "positions": [
    {
      "id": 1,
      "move_mode": "walk",
      "type": "teleport",
      "x": -867.6884765625,
      "y": 2281.365966796875
    },
    {
      "id": 2,
      "move_mode": "walk",
      "type": "path",
      "x": -882.1455078125,
      "y": 2262.399658203125
    },
    {
      "id": 3,
      "move_mode": "walk",
      "type": "path",
      "x": -911.3125,
      "y": 2240.5625
    },
    {
      "id": 4,
      "move_mode": "walk",
      "type": "path",
      "x": -913.88671875,
      "y": 2232.62890625
    }
  ]
}