{
  "info": {
    "authors": [
      {
        "links": "https://github.com/Tooltingsu",
        "name": "Tool_tingsu"
      }
    ],
    "bgi_version": "0.42.3",
    "description": "",
    "name": "15-烬芯花-沃陆之邦右侧-1个",
    "tags": [
      "单手剑角色",
      "大剑角色",
      "长枪角色"
    ],
    "type": "collect",
    "version": "1.0"
  },
  "positions": [
    {
      "action": "force_tp",
      "action_params": "",
      "id": 1,
      "move_mode": "walk",
      "type": "teleport",
      "x": 9838.07,
      "y": -2365.09
    },
    {
      "action": "",
      "action_params": "",
      "id": 2,
      "move_mode": "walk",
      "type": "path",
      "x": 9831.77,
      "y": -2379.29
    },
    {
      "action": "",
      "action_params": "",
      "id": 3,
      "move_mode": "walk",
      "type": "path",
      "x": 9821.96,
      "y": -2394.79
    },
    {
      "action": "",
      "action_params": "",
      "id": 4,
      "move_mode": "walk",
      "type": "path",
      "x": 9821.38,
      "y": -2406.34
    },
    {
      "action": "combat_script",
      "action_params": "attack(0.2)",
      "id": 5,
      "move_mode": "walk",
      "type": "target",
      "x": 9834.85,
      "y": -2417.59
    }
  ]
}
