{
  "info": {
    "name": "须弥鱼贩-珀姆",
    "type": "collect",
    "author": "小鹰划船不用桨",
    "version": "1.0",
    "description": "须弥鱼贩-珀姆",
    "map_name": "Teyvat",
    "bgi_version": "0.45.0"
  },
  "positions": [
    {
      "id": 1,
      "action": "",
      "move_mode": "walk",
      "type": "teleport",
      "x": 2786.9755859375,
      "y": -503.099609375,
      "action_params": ""
    },
    {
      "id": 2,
      "x": 2807.921875,
      "y": -515.51220703125,
      "type": "path",
      "move_mode": "dash",
      "action": "",
      "action_params": ""
    },
    {
      "id": 3,
      "x": 2811.0615234375,
      "y": -509.51171875,
      "type": "path",
      "move_mode": "walk",
      "action": "",
      "action_params": ""
    }
  ]
}